pre_commit_hooks/__init__.py
pre_commit_hooks/poetry_to_requirements.py
poetry_to_requirements-1.0.1.dist-info/METADATA
poetry_to_requirements-1.0.1.dist-info/entry_points.txt
poetry_to_requirements-1.0.1.dist-info/WHEEL
poetry_to_requirements-1.0.1.dist-info/LICENSE
poetry_to_requirements-1.0.1.dist-info/RECORD
