Metadata-Version: 2.1
Name: poetry-to-requirements
Version: 1.0.1
Summary: Pre-commit hook to convert Poetry dependancies to pip requirements.txt.
Home-page: https://github.com/christopherpickering/pre-commit-hooks.git
License: MIT
Author: Christopher Pickering
Author-email: christopher@going.bg
Requires-Python: >=3.7.2,<4.0.0
Classifier: License :: OSI Approved :: MIT License
Classifier: Programming Language :: Python :: 3
Classifier: Programming Language :: Python :: 3.8
Classifier: Programming Language :: Python :: 3.9
Classifier: Programming Language :: Python :: 3.10
Classifier: Programming Language :: Python :: 3.11
Classifier: Programming Language :: Python :: 3
Classifier: Programming Language :: Python :: 3 :: Only
Classifier: Programming Language :: Python :: 3.7
Classifier: Programming Language :: Python :: 3.8
Classifier: Programming Language :: Python :: 3.9
Classifier: Programming Language :: Python :: Implementation :: PyPy
Project-URL: Repository, https://github.com/christopherpickering/pre-commit-hooks.git
